{
  "name": "Трапер — пакет знание",
  "topic": "трапер",
  "seedInterests": false,
  "terms": [
    {
      "term": "Трапер",
      "definition": "Трапер е ловец на животни заради тяхната кожа.",
      "source": "bg.wikipedia.org: Трапер",
      "url": "https://bg.wikipedia.org/wiki/%D0%A2%D1%80%D0%B0%D0%BF%D0%B5%D1%80"
    },
    {
      "term": "Уинипег (езеро)",
      "definition": "Езерото Уинипег е най-голямото езеро в провинция Манитоба.",
      "source": "bg.wikipedia.org: Уинипег (езеро)",
      "url": "https://bg.wikipedia.org/wiki/%D0%A3%D0%B8%D0%BD%D0%B8%D0%BF%D0%B5%D0%B3_(%D0%B5%D0%B7%D0%B5%D1%80%D0%BE)"
    },
    {
      "term": "Прово",
      "definition": "Прово е град в щата Юта, САЩ. Прово е с население от 105 166 жители (2000) и обща площ от 108,20 км². Прово се намира на около 80 км южно от Солт Лейк Сити. Прово се е казвал първоначално Форт Юта, когато е бил създаден през 1849 г. от 33 мормонски семейства от Солт Лейк Сити, но през 1850 г. е преименуван на Прово на Етиен Прово, френски-канадски трапер, който дошъл в района през 1825 г.",
      "source": "bg.wikipedia.org: Прово",
      "url": "https://bg.wikipedia.org/wiki/%D0%9F%D1%80%D0%BE%D0%B2%D0%BE"
    },
    {
      "term": "Етиен Брюле",
      "definition": "Етиен Брюле е френски трапер, търговец на кожи, пътешественик-изследовател.",
      "source": "bg.wikipedia.org: Етиен Брюле",
      "url": "https://bg.wikipedia.org/wiki/%D0%95%D1%82%D0%B8%D0%B5%D0%BD_%D0%91%D1%80%D1%8E%D0%BB%D0%B5"
    },
    {
      "term": "Кит Карсън (пътешественик)",
      "definition": "Кристофър Хустън (Кит) Карсън е американски пътешественик-изследовател, трапер.",
      "source": "bg.wikipedia.org: Кит Карсън (пътешественик)",
      "url": "https://bg.wikipedia.org/wiki/%D0%9A%D0%B8%D1%82_%D0%9A%D0%B0%D1%80%D1%81%D1%8A%D0%BD_(%D0%BF%D1%8A%D1%82%D0%B5%D1%88%D0%B5%D1%81%D1%82%D0%B2%D0%B5%D0%BD%D0%B8%D0%BA)"
    },
    {
      "term": "Уилсън Прайс Хънт",
      "definition": "Уилсън Прайс Хънт е американски трапер, изследовател на Скалистите планини.",
      "source": "bg.wikipedia.org: Уилсън Прайс Хънт",
      "url": "https://bg.wikipedia.org/wiki/%D0%A3%D0%B8%D0%BB%D1%81%D1%8A%D0%BD_%D0%9F%D1%80%D0%B0%D0%B9%D1%81_%D0%A5%D1%8A%D0%BD%D1%82"
    },
    {
      "term": "Джон Колтър",
      "definition": "Джон Колтър е американски трапер и пътешественик-изследовател.",
      "source": "bg.wikipedia.org: Джон Колтър",
      "url": "https://bg.wikipedia.org/wiki/%D0%94%D0%B6%D0%BE%D0%BD_%D0%9A%D0%BE%D0%BB%D1%82%D1%8A%D1%80"
    },
    {
      "term": "Ботино (град)",
      "definition": "Ботино е град в окръг Ботино, Северна Дакота, Съединени щати. Той е окръжен център на окръга и се намира само на 16 километра южно от границата между Канада и Съединените щати. Населението на града е 2255 жители.",
      "source": "bg.wikipedia.org: Ботино (град)",
      "url": "https://bg.wikipedia.org/wiki/%D0%91%D0%BE%D1%82%D0%B8%D0%BD%D0%BE_(%D0%B3%D1%80%D0%B0%D0%B4)"
    },
    {
      "term": "Сивата сова",
      "definition": "Арчибалд Билейни, известен като Сивата сова, е канадски природозащитник, писател, трапер, ловец, роден във Великобритания, починал в Канада.",
      "source": "bg.wikipedia.org: Сивата сова",
      "url": "https://bg.wikipedia.org/wiki/%D0%A1%D0%B8%D0%B2%D0%B0%D1%82%D0%B0_%D1%81%D0%BE%D0%B2%D0%B0"
    },
    {
      "term": "Койот",
      "definition": "Койотът, наричан и прериен вълк, е животно от семейство Кучеви, сродно на домашното куче. Среща се в Северна и Централна Америка. Името му произлиза от испанския изговор на ацтекската дума „койотъл“. Животното е герой на много митове и легенди, разпространени сред редица индиански племена от Северна и отчасти – Централна Америка. Обикновено той се проявява в ролята на трикстер, но в някои случаи и на демиург, който създава света и хората.",
      "source": "bg.wikipedia.org: Койот",
      "url": "https://bg.wikipedia.org/wiki/%D0%9A%D0%BE%D0%B9%D0%BE%D1%82"
    },
    {
      "term": "По границите на Далечния запад",
      "definition": "„По границите на Далечния запад“ е роман на италианския писател Емилио Салгари, издаден през 1908 г.; първа част от неговата трилогия за Дивия Запад.",
      "source": "bg.wikipedia.org: По границите на Далечния запад",
      "url": "https://bg.wikipedia.org/wiki/%D0%9F%D0%BE_%D0%B3%D1%80%D0%B0%D0%BD%D0%B8%D1%86%D0%B8%D1%82%D0%B5_%D0%BD%D0%B0_%D0%94%D0%B0%D0%BB%D0%B5%D1%87%D0%BD%D0%B8%D1%8F_%D0%B7%D0%B0%D0%BF%D0%B0%D0%B4"
    },
    {
      "term": "Кристоф Дюфро дьо ла Жемереи",
      "definition": "Кристоф Дюфро дьо ла Жемереи е канадски изследовател и картограф, племенник на Пиер Готие Варен дьо ла Верандри.",
      "source": "bg.wikipedia.org: Кристоф Дюфро дьо ла Жемереи",
      "url": "https://bg.wikipedia.org/wiki/%D0%9A%D1%80%D0%B8%D1%81%D1%82%D0%BE%D1%84_%D0%94%D1%8E%D1%84%D1%80%D0%BE_%D0%B4%D1%8C%D0%BE_%D0%BB%D0%B0_%D0%96%D0%B5%D0%BC%D0%B5%D1%80%D0%B5%D0%B8"
    },
    {
      "term": "Прерията",
      "definition": "Прерията е исторически роман на американския писател Джеймс Фенимор Купър, издаден през 1827 г. от издателството „Carey, Lea & Carey—Chestnut-Street“ във Филаделфия. Това е последната книга от пенталогията Коженият чорап.",
      "source": "bg.wikipedia.org: Прерията",
      "url": "https://bg.wikipedia.org/wiki/%D0%9F%D1%80%D0%B5%D1%80%D0%B8%D1%8F%D1%82%D0%B0"
    },
    {
      "term": "Жак дьо Нойон",
      "definition": "Жак дьо Нойон е френски трапер и пътешественик-изследовател.",
      "source": "bg.wikipedia.org: Жак дьо Нойон",
      "url": "https://bg.wikipedia.org/wiki/%D0%96%D0%B0%D0%BA_%D0%B4%D1%8C%D0%BE_%D0%9D%D0%BE%D0%B9%D0%BE%D0%BD"
    },
    {
      "term": "Пайет (окръг)",
      "definition": "Окръг Пайет е окръг в щата Айдахо, Съединени американски щати. Площ 1062 km². Население – 23 215 души (2017), 1,51% от населението на щата, гъстота 21,9 души/km². Административен център град Пайет.",
      "source": "bg.wikipedia.org: Пайет (окръг)",
      "url": "https://bg.wikipedia.org/wiki/%D0%9F%D0%B0%D0%B9%D0%B5%D1%82_(%D0%BE%D0%BA%D1%80%D1%8A%D0%B3)"
    },
    {
      "term": "Джедидая Смит",
      "definition": "Джедидая Смит е американски пътешественик-изследовател, картограф, трапер, търговски агент на „Северозападната компания“, търгуваща с ценни животински кожи.",
      "source": "bg.wikipedia.org: Джедидая Смит",
      "url": "https://bg.wikipedia.org/wiki/%D0%94%D0%B6%D0%B5%D0%B4%D0%B8%D0%B4%D0%B0%D1%8F_%D0%A1%D0%BC%D0%B8%D1%82"
    },
    {
      "term": "Крос (езеро)",
      "definition": "Езерото Крос е 8-ото по големина езеро в провинция Манитоба. Площта му заедно с островите в него е 755 км2, която му отрежда 55-о място сред езерата на Канада. Площта само на водното огледало без островите е 590 км2. Надморската височина на водата е 207 м.",
      "source": "bg.wikipedia.org: Крос (езеро)",
      "url": "https://bg.wikipedia.org/wiki/%D0%9A%D1%80%D0%BE%D1%81_(%D0%B5%D0%B7%D0%B5%D1%80%D0%BE)"
    },
    {
      "term": "Призрака на Ляно Естакадо",
      "definition": "„Призрака на Ляно Естакадо“ е роман от 1888 г. на немския автор Карл Май, продължение на творбата му „Синът на ловеца на мечки“, издаден една година по-рано.",
      "source": "bg.wikipedia.org: Призрака на Ляно Естакадо",
      "url": "https://bg.wikipedia.org/wiki/%D0%9F%D1%80%D0%B8%D0%B7%D1%80%D0%B0%D0%BA%D0%B0_%D0%BD%D0%B0_%D0%9B%D1%8F%D0%BD%D0%BE_%D0%95%D1%81%D1%82%D0%B0%D0%BA%D0%B0%D0%B4%D0%BE"
    },
    {
      "term": "Бенджамин Люис Бонвил",
      "definition": "Бенджамин Люис (Луи) Бонвил е американски офицер от френски произход, трапер, изследовател на Американския Запад. Известен е със своите експедиции в Орегон и района на Големия басейн.",
      "source": "bg.wikipedia.org: Бенджамин Люис Бонвил",
      "url": "https://bg.wikipedia.org/wiki/%D0%91%D0%B5%D0%BD%D0%B4%D0%B6%D0%B0%D0%BC%D0%B8%D0%BD_%D0%9B%D1%8E%D0%B8%D1%81_%D0%91%D0%BE%D0%BD%D0%B2%D0%B8%D0%BB"
    },
    {
      "term": "Сипиуеск",
      "definition": "Езерото Сипиуеск е 12-о по големина езеро в провинция Манитоба. Площта му заедно с островите в него е 454 км2, която му отрежда 106-о място сред езерата на Канада. Площта само на водното огледало без островите е 346 км2. Надморската височина на водата е 183 м.",
      "source": "bg.wikipedia.org: Сипиуеск",
      "url": "https://bg.wikipedia.org/wiki/%D0%A1%D0%B8%D0%BF%D0%B8%D1%83%D0%B5%D1%81%D0%BA"
    },
    {
      "term": "Плейгрин",
      "definition": "Езерото Плейгрийн е 9-о по големина езеро в провинция Манитоба. Площта му заедно с островите в него е 657 км2, която му отрежда 66-о място сред езерата на Канада. Площта само на водното огледало без островите е 652 км2. Надморската височина на водата е 217 м.",
      "source": "bg.wikipedia.org: Плейгрин",
      "url": "https://bg.wikipedia.org/wiki/%D0%9F%D0%BB%D0%B5%D0%B9%D0%B3%D1%80%D0%B8%D0%BD"
    },
    {
      "term": "Пийс",
      "definition": "Пийс е река в северозападната част на Канада, провинции Британска Колумбия и Албърта. Дължината ѝ от 1923 km, заедно с лявата съставяща я река Финли ѝ отрежда 7-о място сред реките на Канада. Дължината само на река Пийс е 1431 km, която я прави в действителност 3-та по дължина изцяло канадска река след Маккензи и Чърчил.",
      "source": "bg.wikipedia.org: Пийс",
      "url": "https://bg.wikipedia.org/wiki/%D0%9F%D0%B8%D0%B9%D1%81"
    },
    {
      "term": "Горско езеро",
      "definition": "Горско езеро е 6-о по големина езеро в провинция Онтарио. Площта му, заедно с островите в него е 4349 км2, като канадската площ е 3149 км2, която му отрежда 16-о място сред езерата на Канада. Надморската височина на водата е 323 м.",
      "source": "bg.wikipedia.org: Горско езеро",
      "url": "https://bg.wikipedia.org/wiki/%D0%93%D0%BE%D1%80%D1%81%D0%BA%D0%BE_%D0%B5%D0%B7%D0%B5%D1%80%D0%BE"
    },
    {
      "term": "Тайните на Киетуд",
      "definition": "„Тайните на Киетуд“ е аржентински филм от 2018 година, драма на режисьора Пабло Траперо по негов собствен сценарий.",
      "source": "bg.wikipedia.org: Тайните на Киетуд",
      "url": "https://bg.wikipedia.org/wiki/%D0%A2%D0%B0%D0%B9%D0%BD%D0%B8%D1%82%D0%B5_%D0%BD%D0%B0_%D0%9A%D0%B8%D0%B5%D1%82%D1%83%D0%B4"
    },
    {
      "term": "Отвъд широката Мисури",
      "definition": "„Отвъд широката Мисури“ е американски уестърн филм, излязъл по екраните през 1951 година, режисиран от Уилям Уелман с участието на Кларк Гейбъл в главната роля.",
      "source": "bg.wikipedia.org: Отвъд широката Мисури",
      "url": "https://bg.wikipedia.org/wiki/%D0%9E%D1%82%D0%B2%D1%8A%D0%B4_%D1%88%D0%B8%D1%80%D0%BE%D0%BA%D0%B0%D1%82%D0%B0_%D0%9C%D0%B8%D1%81%D1%83%D1%80%D0%B8"
    },
    {
      "term": "Рейни (езеро)",
      "definition": "Езерото Рейни е 11-о по големина езеро в провинция Онтарио. Площта му, заедно с островите в него е 932 км2, като канадската площ е 741 км2, която му отрежда 57-о място сред езерата на Канада. Надморската височина на водата е 338 м.",
      "source": "bg.wikipedia.org: Рейни (езеро)",
      "url": "https://bg.wikipedia.org/wiki/%D0%A0%D0%B5%D0%B9%D0%BD%D0%B8_(%D0%B5%D0%B7%D0%B5%D1%80%D0%BE)"
    },
    {
      "term": "ФК Лудогорец 2003",
      "definition": "ФК „Лудогорец-2003“ е бивш футболен клуб от Разград. Основан през 1945 г. от сливането на „Ботев“ (1920), „Бели Лом“, „Бенковски“, „Вихър“ и „Левски“.",
      "source": "bg.wikipedia.org: ФК Лудогорец 2003",
      "url": "https://bg.wikipedia.org/wiki/%D0%A4%D0%9A_%D0%9B%D1%83%D0%B4%D0%BE%D0%B3%D0%BE%D1%80%D0%B5%D1%86_2003"
    },
    {
      "term": "Сидър (езеро)",
      "definition": "Езерото Сидър е 5-о по големина езеро в провинция Манитоба. Площта му заедно с островите в него е 1353 км2, която му отрежда 33-то място сред езерата на Канада. Площта само на водното огледало без островите е 1321 км2. Надморската височина на водата е 253 м.",
      "source": "bg.wikipedia.org: Сидър (езеро)",
      "url": "https://bg.wikipedia.org/wiki/%D0%A1%D0%B8%D0%B4%D1%8A%D1%80_(%D0%B5%D0%B7%D0%B5%D1%80%D0%BE)"
    },
    {
      "term": "Горно езеро",
      "definition": "Горното езеро е най-голямото от петте Големи езера в Северна Америка. На север граничи с канадската провинция Онтарио и с американския щат Минесота, а на юг – с американските щати Уисконсин и Мичиган. Това е най-голямото сладководно езеро в света по площ, ако се приеме че езерото Хюрън и езерото Мичиган са два отделни водни басейна.. Площта само на канадската територия на езерото е 28 700 км2, като по този начин то е 3-то по големина езеро в Канада и 2-рото в провинция Онтарио. Надморската височина на водата е 183 м.",
      "source": "bg.wikipedia.org: Горно езеро",
      "url": "https://bg.wikipedia.org/wiki/%D0%93%D0%BE%D1%80%D0%BD%D0%BE_%D0%B5%D0%B7%D0%B5%D1%80%D0%BE"
    },
    {
      "term": "Бъфало Бил",
      "definition": "Уилям Фредерик „Бъ̀фало Бил“ Коуди е прочут американски ловец на бизони и шоумен, роден е в щата Айова, близо до град Ле Клер. Той е една от най-колоритните фигури на Дивия запад.",
      "source": "bg.wikipedia.org: Бъфало Бил",
      "url": "https://bg.wikipedia.org/wiki/%D0%91%D1%8A%D1%84%D0%B0%D0%BB%D0%BE_%D0%91%D0%B8%D0%BB"
    },
    {
      "term": "Човек от булеварда на Капуцините",
      "definition": "Човекът от булеварда на капуцините е съветски игрален филм, комедиен уестърн на Алла Сурикова по сценарий на Едуард Акопов. Премиерата е на 23 юни 1987 г. в московското кино \"Мир\". 60 милиона зрители са гледали филма през годината на излизане. Предпоследната роля на Андрей Миронов в киното.",
      "source": "bg.wikipedia.org: Човек от булеварда на Капуцините",
      "url": "https://bg.wikipedia.org/wiki/%D0%A7%D0%BE%D0%B2%D0%B5%D0%BA_%D0%BE%D1%82_%D0%B1%D1%83%D0%BB%D0%B5%D0%B2%D0%B0%D1%80%D0%B4%D0%B0_%D0%BD%D0%B0_%D0%9A%D0%B0%D0%BF%D1%83%D1%86%D0%B8%D0%BD%D0%B8%D1%82%D0%B5"
    },
    {
      "term": "Майкъл Пунке",
      "definition": "Майкъл Пунке е американски политически анализатор и консултант, политик, адвокат и писател – автор на произведения в жанровете исторически роман и документалистика.",
      "source": "bg.wikipedia.org: Майкъл Пунке",
      "url": "https://bg.wikipedia.org/wiki/%D0%9C%D0%B0%D0%B9%D0%BA%D1%8A%D0%BB_%D0%9F%D1%83%D0%BD%D0%BA%D0%B5"
    },
    {
      "term": "Експедиция на Луис и Кларк",
      "definition": "Експедицията на Мериуедър Луис и Уилям Кларк през 1804 – 1806 г., известна също като Корпус за открития, е първата експедиция от САЩ, прекосила територията между Атлантическия и Тихия океан и върнала се обратно.",
      "source": "bg.wikipedia.org: Експедиция на Луис и Кларк",
      "url": "https://bg.wikipedia.org/wiki/%D0%95%D0%BA%D1%81%D0%BF%D0%B5%D0%B4%D0%B8%D1%86%D0%B8%D1%8F_%D0%BD%D0%B0_%D0%9B%D1%83%D0%B8%D1%81_%D0%B8_%D0%9A%D0%BB%D0%B0%D1%80%D0%BA"
    },
    {
      "term": "Уестърн",
      "definition": "Уестърн е жанр в изкуството, характерен предимно за САЩ, в художествената литература, кинематографията, телевизията, живописта и други изобразителни изкуства.",
      "source": "bg.wikipedia.org: Уестърн",
      "url": "https://bg.wikipedia.org/wiki/%D0%A3%D0%B5%D1%81%D1%82%D1%8A%D1%80%D0%BD"
    },
    {
      "term": "RDMK",
      "definition": "RDMK е българска музикална група, създадена през 2012 г. от Радослав Радославов - Rxdi, Веселин Дулев - Duli D (вокал), Асен Кукушев - Kukusheff (вокал) и Александър Митов - Muden MC (вокал). В този си състав те имат издаден един албум – „The All Boom“ (2017). В него са включени популярните песни на групата от създаването като „Бича си айляк“, \"Дневен ред\", \"Мене не! Maybe\" и др., както и нови, неиздавани песни. През 2019 г. рапърът на RDMK, Александър Митов-Muden MC решава да напусне групата и групата продължава в състав от трима. След едногодишна пауза, през (2020) подновяват активността си и започват да създават песни с повече поп звучене.",
      "source": "bg.wikipedia.org: RDMK",
      "url": "https://bg.wikipedia.org/wiki/RDMK"
    },
    {
      "term": "Медард дьо Грозейле",
      "definition": "Медард Шуар дьо Грозейле е френски търговец на кожи, изследовател на Северна Америка.",
      "source": "bg.wikipedia.org: Медард дьо Грозейле",
      "url": "https://bg.wikipedia.org/wiki/%D0%9C%D0%B5%D0%B4%D0%B0%D1%80%D0%B4_%D0%B4%D1%8C%D0%BE_%D0%93%D1%80%D0%BE%D0%B7%D0%B5%D0%B9%D0%BB%D0%B5"
    },
    {
      "term": "Йелоустоун (национален парк)",
      "definition": "Национален парк „Йелоустоун“ е името на първия национален парк. Той се намира в северозападните части на САЩ, предимно на територията на Уайоминг, отделни части от Монтана и Скалистите планини в Айдахо и обхваща площ от 8980 km². Създаден на 1 март 1872 г., той е първата в света защитена природна територия. Той е част от екосистема с планински масиви, езера, реки и гори. Едни от най-големите му забележителности са вулканичните скали от черен обсидиан и многото гейзери и горещи извори. Най-големият и най-високият гейзер е „Стиймбоут“. Сред най-известните е и гейзерът „Олд Фейтфул“, наречен така заради точността на изригванията си. Едно изригване може да изстреля между 14 и 32 000 литра вода …",
      "source": "bg.wikipedia.org: Йелоустоун (национален парк)",
      "url": "https://bg.wikipedia.org/wiki/%D0%99%D0%B5%D0%BB%D0%BE%D1%83%D1%81%D1%82%D0%BE%D1%83%D0%BD_(%D0%BD%D0%B0%D1%86%D0%B8%D0%BE%D0%BD%D0%B0%D0%BB%D0%B5%D0%BD_%D0%BF%D0%B0%D1%80%D0%BA)"
    },
    {
      "term": "Фридрих Герстекер",
      "definition": "Фридрих Герстекер е германски пътешественик, преводач и писател, автор на пътеписи и приключенски романи предимно за младежката аудитория.",
      "source": "bg.wikipedia.org: Фридрих Герстекер",
      "url": "https://bg.wikipedia.org/wiki/%D0%A4%D1%80%D0%B8%D0%B4%D1%80%D0%B8%D1%85_%D0%93%D0%B5%D1%80%D1%81%D1%82%D0%B5%D0%BA%D0%B5%D1%80"
    },
    {
      "term": "Владимир Мусаков (преводач)",
      "definition": "Владимир Мусаков е изтъкнат български преводач от немски и английски език.\nПретворил е над 100 творби от големи автори като Ерих Кестнер, Хайнрих Бьол, Лион Фойхтвангер, Гьоте, Шилер, Хайнрих Ман, Карл Май, стихове от Кестнер, Лонгфелоу, Уитман, Рилке, пиеси от Брехт, Голсуърти и др.",
      "source": "bg.wikipedia.org: Владимир Мусаков (преводач)",
      "url": "https://bg.wikipedia.org/wiki/%D0%92%D0%BB%D0%B0%D0%B4%D0%B8%D0%BC%D0%B8%D1%80_%D0%9C%D1%83%D1%81%D0%B0%D0%BA%D0%BE%D0%B2_(%D0%BF%D1%80%D0%B5%D0%B2%D0%BE%D0%B4%D0%B0%D1%87)"
    },
    {
      "term": "Джон Фримонт",
      "definition": "Джон Чарлз Фримонт е американски военен топограф, политик, изследовател на западните части на САЩ.",
      "source": "bg.wikipedia.org: Джон Фримонт",
      "url": "https://bg.wikipedia.org/wiki/%D0%94%D0%B6%D0%BE%D0%BD_%D0%A4%D1%80%D0%B8%D0%BC%D0%BE%D0%BD%D1%82"
    }
  ],
  "entries": []
}